{"nodes": [{"id": "auth_jwt_create_token", "label": "create_access_token", "file_type": "code", "source_file": "auth/jwt_handler.py", "source_location": null, "source_url": null, "captured_at": null, "author": null, "contributor": null}, {"id": "auth_jwt_decode_token", "label": "decode_token", "file_type": "code", "source_file": "auth/jwt_handler.py", "source_location": null, "source_url": null, "captured_at": null, "author": null, "contributor": null}, {"id": "auth_jwt_hash_password", "label": "hash_password (bcrypt)", "file_type": "code", "source_file": "auth/jwt_handler.py", "source_location": null, "source_url": null, "captured_at": null, "author": null, "contributor": null}, {"id": "auth_jwt_verify_password", "label": "verify_password", "file_type": "code", "source_file": "auth/jwt_handler.py", "source_location": null, "source_url": null, "captured_at": null, "author": null, "contributor": null}, {"id": "auth_jwt_encrypt_api_key", "label": "encrypt_api_key (Fernet)", "file_type": "code", "source_file": "auth/jwt_handler.py", "source_location": null, "source_url": null, "captured_at": null, "author": null, "contributor": null}, {"id": "auth_jwt_decrypt_api_key", "label": "decrypt_api_key (Fernet)", "file_type": "code", "source_file": "auth/jwt_handler.py", "source_location": null, "source_url": null, "captured_at": null, "author": null, "contributor": null}, {"id": "auth_jwt_derive_fernet_key", "label": "_derive_fernet_key (sha256)", "file_type": "code", "source_file": "auth/jwt_handler.py", "source_location": null, "source_url": null, "captured_at": null, "author": null, "contributor": null}, {"id": "ext_auth_jwt_handler", "label": "auth.jwt_handler", "file_type": "code", "source_file": "auth/jwt_handler.py", "source_location": null, "source_url": null, "captured_at": null, "author": null, "contributor": null}], "edges": [{"source": "auth_jwt_create_token", "target": "config_settings", "relation": "depends_on", "confidence": "EXTRACTED", "confidence_score": 1.0, "source_file": "auth/jwt_handler.py", "source_location": null, "weight": 1.0}, {"source": "auth_jwt_decode_token", "target": "config_settings", "relation": "depends_on", "confidence": "EXTRACTED", "confidence_score": 1.0, "source_file": "auth/jwt_handler.py", "source_location": null, "weight": 1.0}, {"source": "auth_jwt_encrypt_api_key", "target": "auth_jwt_derive_fernet_key", "relation": "calls", "confidence": "EXTRACTED", "confidence_score": 1.0, "source_file": "auth/jwt_handler.py", "source_location": null, "weight": 1.0}, {"source": "auth_jwt_decrypt_api_key", "target": "auth_jwt_derive_fernet_key", "relation": "calls", "confidence": "EXTRACTED", "confidence_score": 1.0, "source_file": "auth/jwt_handler.py", "source_location": null, "weight": 1.0}, {"source": "auth_jwt_derive_fernet_key", "target": "config_settings", "relation": "depends_on", "confidence": "EXTRACTED", "confidence_score": 1.0, "source_file": "auth/jwt_handler.py", "source_location": null, "weight": 1.0}, {"source": "auth_jwt_encrypt_api_key", "target": "auth_jwt_decrypt_api_key", "relation": "semantically_similar_to", "confidence": "INFERRED", "confidence_score": 0.95, "source_file": "auth/jwt_handler.py", "source_location": null, "weight": 1.0}], "hyperedges": []}