{"nodes": [{"id": "router_chat", "label": "routers/chat.py", "file_type": "code", "source_file": "routers/chat.py", "source_location": null, "source_url": null, "captured_at": null, "author": null, "contributor": null}, {"id": "router_chat_message", "label": "chat.chat_message", "file_type": "code", "source_file": "routers/chat.py", "source_location": null, "source_url": null, "captured_at": null, "author": null, "contributor": null}], "edges": [{"source": "router_chat_message", "target": "ext_auth_dependencies", "relation": "depends_on", "confidence": "EXTRACTED", "confidence_score": 1.0, "source_file": "routers/chat.py", "source_location": null, "weight": 1.0}, {"source": "router_chat_message", "target": "ext_agents_chatbot_graph", "relation": "calls", "confidence": "EXTRACTED", "confidence_score": 1.0, "source_file": "routers/chat.py", "source_location": null, "weight": 1.0}, {"source": "router_chat_message", "target": "ext_agents_state", "relation": "references", "confidence": "EXTRACTED", "confidence_score": 1.0, "source_file": "routers/chat.py", "source_location": null, "weight": 1.0}, {"source": "router_chat_message", "target": "service_embedding_invalid_api_key_error", "relation": "references", "confidence": "EXTRACTED", "confidence_score": 1.0, "source_file": "routers/chat.py", "source_location": null, "weight": 1.0}, {"source": "router_chat_message", "target": "service_embedding_rate_limit_error", "relation": "references", "confidence": "EXTRACTED", "confidence_score": 1.0, "source_file": "routers/chat.py", "source_location": null, "weight": 1.0}, {"source": "router_chat_message", "target": "router_jd_match_match", "relation": "semantically_similar_to", "confidence": "INFERRED", "confidence_score": 0.9, "source_file": "routers/chat.py", "source_location": null, "weight": 1.0}], "hyperedges": []}